python_sql_generator/__init__.py
python_sql_generator/python_sql_generator.py
python_sql_generator-0.9.7.dist-info/LICENSE
python_sql_generator-0.9.7.dist-info/METADATA
python_sql_generator-0.9.7.dist-info/WHEEL
python_sql_generator-0.9.7.dist-info/top_level.txt
python_sql_generator-0.9.7.dist-info/RECORD
