Metadata-Version: 2.1
Name: python-sql-generator
Version: 0.9.7
Summary: Simple Package for generating SQL from Dictionary Objects.
Home-page: https://github.com/tmuzzin/PythonSQLGenerator
Author: Tim Muzzin
Author-email: timmuzzin@gmail.com
License: UNKNOWN
Platform: UNKNOWN
Classifier: Programming Language :: Python :: 2.7
Classifier: Programming Language :: Python :: 3.7
Classifier: License :: OSI Approved :: MIT License
Classifier: Operating System :: OS Independent
